odoo10_addon_web_widget_color-10.0.1.0.1-py2.7-nspkg.pth
odoo/addons/web_widget_color/README.rst
odoo/addons/web_widget_color/__init__.py
odoo/addons/web_widget_color/__manifest__.py
odoo/addons/web_widget_color/i18n/web_widget_color.pot
odoo/addons/web_widget_color/images/form_view.png
odoo/addons/web_widget_color/images/list_view.png
odoo/addons/web_widget_color/images/picker.png
odoo/addons/web_widget_color/static/description/icon.png
odoo/addons/web_widget_color/static/lib/jscolor/arrow.gif
odoo/addons/web_widget_color/static/lib/jscolor/cross.gif
odoo/addons/web_widget_color/static/lib/jscolor/demo.html
odoo/addons/web_widget_color/static/lib/jscolor/hs.png
odoo/addons/web_widget_color/static/lib/jscolor/hv.png
odoo/addons/web_widget_color/static/lib/jscolor/jscolor.js
odoo/addons/web_widget_color/static/src/css/widget.css
odoo/addons/web_widget_color/static/src/js/widget.js
odoo/addons/web_widget_color/static/src/xml/widget.xml
odoo/addons/web_widget_color/view/web_widget_color_view.xml
odoo10_addon_web_widget_color-10.0.1.0.1.dist-info/METADATA
odoo10_addon_web_widget_color-10.0.1.0.1.dist-info/RECORD
odoo10_addon_web_widget_color-10.0.1.0.1.dist-info/WHEEL
odoo10_addon_web_widget_color-10.0.1.0.1.dist-info/namespace_packages.txt
odoo10_addon_web_widget_color-10.0.1.0.1.dist-info/top_level.txt
